millrun/__init__.py
millrun/cli.py
millrun/millrun.py
millrun-0.3.0.dist-info/entry_points.txt
millrun-0.3.0.dist-info/licenses/LICENSE
millrun-0.3.0.dist-info/WHEEL
millrun-0.3.0.dist-info/METADATA
millrun-0.3.0.dist-info/RECORD
