Metadata-Version: 2.4
Name: millrun
Version: 0.3.0
Summary: Millrun: A Python library and CLI tool to automate the execution of notebooks
Author-email: Connor Ferster <connor@structuralpython.com>
Requires-Python: >=3.10
License-File: LICENSE
Requires-Dist: papermill>=2.6.0
Requires-Dist: rich
Requires-Dist: ruamel-yaml>=0.18.15
Requires-Dist: typer>=0.16.0
